c4m/__init__.py
c4m/PySpice/__init__.py
c4m/PySpice/Config/ConfigInstall.py
c4m/PySpice/Config/__init__.py
c4m/PySpice/Config/logging.yml
c4m/PySpice/DeviceLibrary/__init__.py
c4m/PySpice/Doc/ExampleTools.py
c4m/PySpice/Doc/__init__.py
c4m/PySpice/Logging/Logging.py
c4m/PySpice/Logging/__init__.py
c4m/PySpice/Math/Calculus.py
c4m/PySpice/Math/__init__.py
c4m/PySpice/Physics/MaterialProperties.py
c4m/PySpice/Physics/PhysicalConstants.py
c4m/PySpice/Physics/Resistor.py
c4m/PySpice/Physics/SemiConductor.py
c4m/PySpice/Physics/__init__.py
c4m/PySpice/Plot/BodeDiagram.py
c4m/PySpice/Plot/__init__.py
c4m/PySpice/Probe/Plot.py
c4m/PySpice/Probe/WaveForm.py
c4m/PySpice/Probe/__init__.py
c4m/PySpice/Scripts/__init__.py
c4m/PySpice/Scripts/cir2py.py
c4m/PySpice/Scripts/pyspice_post_installation.py
c4m/PySpice/Spice/BasicElement.py
c4m/PySpice/Spice/ElementParameter.py
c4m/PySpice/Spice/HighLevelElement.py
c4m/PySpice/Spice/Library.py
c4m/PySpice/Spice/Netlist.py
c4m/PySpice/Spice/Parser.py
c4m/PySpice/Spice/RawFile.py
c4m/PySpice/Spice/Simulation.py
c4m/PySpice/Spice/__init__.py
c4m/PySpice/Spice/Expression/Ast.py
c4m/PySpice/Spice/Expression/Parser.py
c4m/PySpice/Spice/Expression/__init__.py
c4m/PySpice/Spice/NgSpice/RawFile.py
c4m/PySpice/Spice/NgSpice/Server.py
c4m/PySpice/Spice/NgSpice/Shared.py
c4m/PySpice/Spice/NgSpice/Simulation.py
c4m/PySpice/Spice/NgSpice/SimulationType.py
c4m/PySpice/Spice/NgSpice/__init__.py
c4m/PySpice/Spice/NgSpice/api.h
c4m/PySpice/Spice/Xyce/RawFile.py
c4m/PySpice/Spice/Xyce/Server.py
c4m/PySpice/Spice/Xyce/Simulation.py
c4m/PySpice/Spice/Xyce/__init__.py
c4m/PySpice/Tools/EnumFactory.py
c4m/PySpice/Tools/File.py
c4m/PySpice/Tools/Path.py
c4m/PySpice/Tools/StringTools.py
c4m/PySpice/Tools/__init__.py
c4m/PySpice/Unit/SiUnits.py
c4m/PySpice/Unit/Unit.py
c4m/PySpice/Unit/__init__.py
tasks/__init__.py
tasks/anaconda.py
tasks/cir2py-libraries
tasks/clean.py
tasks/doc.py
tasks/git.py
tasks/ngspice.py
tasks/release.py
tasks/test.py
c4m_PySpice-1.4.3.post1.dist-info/LICENSE.txt
c4m_PySpice-1.4.3.post1.dist-info/METADATA
c4m_PySpice-1.4.3.post1.dist-info/WHEEL
c4m_PySpice-1.4.3.post1.dist-info/entry_points.txt
c4m_PySpice-1.4.3.post1.dist-info/top_level.txt
c4m_PySpice-1.4.3.post1.dist-info/RECORD
