Metadata-Version: 2.1
Name: c4m-PySpice
Version: 1.4.3.post1
Summary: Temporary fork of PySpice with extra commits
Home-page: https://gitlab.com/Chips4Makers/c4m-PySpice
Author: Staf Verhaegen
Author-email: staf@fibraservi.eu
Maintainer: Staf Verhaegen
Maintainer-email: staf@fibraservi.eu
License: GPLv3
Project-URL: Code, https://gitlab.com/Chips4Makers/c4m-PySpice
Project-URL: Issue Tracker, https://gitlab.com/Chips4Makers/c4m-PySpice/issues
Keywords: ngspice,xyce,spice,berkeley,electronic,circuit,simulation,simulator
Platform: any
Classifier: Topic :: Scientific/Engineering
Classifier: Intended Audience :: Education
Classifier: Development Status :: 5 - Production/Stable
Classifier: License :: OSI Approved :: GNU General Public License (GPL)
Classifier: Operating System :: OS Independent
Classifier: Programming Language :: Python :: 3.6
Requires-Python: >=3.6
Requires-Dist: PyYAML (>=5.3)
Requires-Dist: cffi (>=1.14)
Requires-Dist: matplotlib (>=3.2)
Requires-Dist: numpy (>=1.18)
Requires-Dist: ply (>=3.11)
Requires-Dist: scipy (>=1.4)
Requires-Dist: requests (>=2.23)
